{
  "Id": 1,
  "Name": "Majkel",
  "Email": "xzcbawwafas@hotmail.com",
  "Address": "Wiejska 13, 13-124 Warszawa""
}; {
  "Id": 2,
  "Name": "Marek",
  "Email": "czbargaaw@o2.pl",
  "Address": "Pokątna 1, 12-523 Majdanek"
};
{
  "Id": 3,
  "Name": "Magda",
  "Email": "nkaowacv@wp.pl",
  "Address": "Farmerska 60, 29-465 Gliwice"
}; {
  "Id": 4,
  "Name": "Wojtek",
  "Email": "azxvawgs3ada@wp.pl",
  "Address": "Błotna 69, 25-435 Olsztyn"
};
{
  "Id": 5,
  "Name": "Mariusz",
  "Email": "zcbawf@wp.pl",
  "Address": "Grzybiczna 14, 12-646 Katowice"
}; {
  "Id": 6,
  "Name": "Tymek",
  "Email": "adzxvbsa@wp.pl",
  "Address": "Miejska 4, 16-546 Białystok"
};
{
  "Id": 7,
  "Name": "Martusia",
  "Email": "asdczxcz@wp.pl",
  "Address": "Makreli 32, 64-236 Gdynia"
}; {
  "Id": 8,
  "Name": "Magda",
  "Email": "vzxzw@wp.pl",
  "Address": "Mokra 66, 26-464 Leżajsk"
};
{
  "Id": 9,
  "Name": "Kacperek",
  "Email": "Imdevops@wp.pl",
  "Address": "Sucha 33, 45-684 Turbia"
}; {
  "Id": 10,
  "Name": "Piotrek",
  "Email": "wasdf@wp.pl",
  "Address": "Płaska 269, 26-749 Piaseczno"
};
